day9/day9.sv
module binToGray #(parameter WID = 4)(input wire [WID-1:0]bin, output wire [WID-1:0]gray);
    // Gray code conversion: G[i] = B[i] ^ B[i+1]
    assign gray[WID-1] = bin[WID-1]; 
    genvar i;
    generate
        for (i = WID-2; i >= 0; i--) begin 
            assign gray[i] = bin[i] ^ bin[i+1];
        end
    endgenerate
endmodule

day9/day9_tb.sv
`timescale 1ns/1ps  
`include "day9.sv"

module binToGray_tb();
    localparam WID = 4;

    logic [WID-1:0] bin;
    logic [WID-1:0] gray;

    binToGray #(WID) B2G(.bin(bin), .gray(gray));

    initial begin
        for (int i = 0; i < (1 << WID); i++) begin
            bin = i;
            #10;
            $display("bin = %d (0x%h), gray = %b (0x%h)", bin, bin, gray, gray);
        end
        $finish();
    end

    initial begin
        $dumpfile("binToGray_tb.vcd");
        $dumpvars(0, binToGray_tb);
    end
endmodule

day9/binToGray_tb.vcd
$date
	Fri Jul 11 16:22:16 2025
$end
$version
	Icarus Verilog
$end
$timescale
	1ps
$end
$scope module binToGray_tb $end
$var wire 4 ! gray [3:0] $end
$var parameter 32 " WID $end
$var reg 4 # bin [3:0] $end
$scope module B2G $end
$var wire 4 $ bin [3:0] $end
$var wire 4 % gray [3:0] $end
$var parameter 32 & WID $end
$scope begin genblk1[0] $end
$var parameter 2 ' i $end
$upscope $end
$scope begin genblk1[1] $end
$var parameter 2 ( i $end
$upscope $end
$scope begin genblk1[2] $end
$var parameter 3 ) i $end
$upscope $end
$upscope $end
$scope begin $ivl_for_loop0 $end
$var integer 32 * i [31:0] $end
$upscope $end
$upscope $end
$enddefinitions $end
$comment Show the parameter values. $end
$dumpall
b10 )
b1 (
b0 '
b100 &
b100 "
$end
#0
$dumpvars
b0 *
b0 %
b0 $
b0 #
b0 !
$end
#10000
b1 !
b1 %
b1 #
b1 $
b1 *
#20000
b11 !
b11 %
b10 #
b10 $
b10 *
#30000
b10 !
b10 %
b11 #
b11 $
b11 *
#40000
b110 !
b110 %
b100 #
b100 $
b100 *
#50000
b111 !
b111 %
b101 #
b101 $
b101 *
#60000
b101 !
b101 %
b110 #
b110 $
b110 *
#70000
b100 !
b100 %
b111 #
b111 $
b111 *
#80000
b1100 !
b1100 %
b1000 #
b1000 $
b1000 *
#90000
b1101 !
b1101 %
b1001 #
b1001 $
b1001 *
#100000
b1111 !
b1111 %
b1010 #
b1010 $
b1010 *
#110000
b1110 !
b1110 %
b1011 #
b1011 $
b1011 *
#120000
b1010 !
b1010 %
b1100 #
b1100 $
b1100 *
#130000
b1011 !
b1011 %
b1101 #
b1101 $
b1101 *
#140000
b1001 !
b1001 %
b1110 #
b1110 $
b1110 *
#150000
b1000 !
b1000 %
b1111 #
b1111 $
b1111 *
#160000
b10000 *
