day11/day11.sv
module seq_detect(input wire clk, rst, data, output wire detected);
// Sequence Detector for "1101_1001" pattern
localparam SEQ = 8'b1101_1001;

logic [7:0]shift_reg;
logic [7:0]next_shift;

always_ff @(posedge clk or posedge rst) begin
    if (rst) shift_reg <= 8'h00;
    else shift_reg <= next_shift;
end

assign next_shift = {shift_reg[6:0], data};
assign detected = (shift_reg == SEQ);

endmodule

day11/day11_tb.sv
`timescale 1ns/1ps
`include "day11.sv"

module seq_detect_tb();
logic clk = 0, rst, data;
logic detected;

seq_detect SEQ_DETECT(.clk(clk), .rst(rst), .data(data), .detected(detected));

always #5 clk = ~clk;

initial begin
    rst = 1; data = 0;
    @(posedge clk);
    @(posedge clk);
    rst = 0; 
    
    // Send correct sequence: 1101_1001
    @(negedge clk); data = 1; // 1st bit: 1
    @(negedge clk); data = 1; // 2nd bit: 1
    @(negedge clk); data = 0; // 3rd bit: 0
    @(negedge clk); data = 1; // 4th bit: 1
    @(negedge clk); data = 1; // 5th bit: 1
    @(negedge clk); data = 0; // 6th bit: 0
    @(negedge clk); data = 0; // 7th bit: 0
    @(negedge clk); data = 1; // 8th bit: 1 (complete sequence)
    
    repeat(3) @(posedge clk); // Wait to see detection
    
    // Test with some random data after detection
    @(negedge clk); data = 0;
    @(negedge clk); data = 1;
    @(negedge clk); data = 0;
    
    repeat(5) @(posedge clk);
    $finish();
end

initial begin
    $dumpfile("seq_detect_tb.vcd");
    $dumpvars(0, seq_detect_tb);
end
endmodule

day11/seq_detect_tb.vcd
$date
	Sat Jul 12 10:50:28 2025
$end
$version
	Icarus Verilog
$end
$timescale
	1ps
$end
$scope module seq_detect_tb $end
$var wire 1 ! detected $end
$var reg 1 " clk $end
$var reg 1 # data $end
$var reg 1 $ rst $end
$scope module SEQ_DETECT $end
$var wire 1 " clk $end
$var wire 1 # data $end
$var wire 1 $ rst $end
$var wire 8 % next_shift [7:0] $end
$var wire 1 ! detected $end
$var parameter 8 & SEQ $end
$var reg 8 ' shift_reg [7:0] $end
$upscope $end
$upscope $end
$enddefinitions $end
$comment Show the parameter values. $end
$dumpall
b11011001 &
$end
#0
$dumpvars
b0 '
b0 %
1$
0#
0"
0!
$end
#5000
1"
#10000
0"
#15000
0$
1"
#20000
b1 %
1#
0"
#25000
b11 %
b1 '
1"
#30000
0"
#35000
b111 %
b11 '
1"
#40000
b110 %
0#
0"
#45000
b1100 %
b110 '
1"
#50000
b1101 %
1#
0"
#55000
b11011 %
b1101 '
1"
#60000
0"
#65000
b110111 %
b11011 '
1"
#70000
b110110 %
0#
0"
#75000
b1101100 %
b110110 '
1"
#80000
0"
#85000
b11011000 %
b1101100 '
1"
#90000
b11011001 %
1#
0"
#95000
b10110011 %
1!
b11011001 '
1"
#100000
0"
#105000
b1100111 %
0!
b10110011 '
1"
#110000
0"
#115000
b11001111 %
b1100111 '
1"
#120000
b11001110 %
0#
0"
#125000
b10011100 %
b11001110 '
1"
#130000
b10011101 %
1#
0"
#135000
b111011 %
b10011101 '
1"
#140000
b111010 %
0#
0"
#145000
b1110100 %
b111010 '
1"
#150000
0"
#155000
b11101000 %
b1110100 '
1"
#160000
0"
#165000
b11010000 %
b11101000 '
1"
#170000
0"
#175000
b10100000 %
b11010000 '
1"
#180000
0"
#185000
b1000000 %
b10100000 '
1"
