day5/day5.sv
// an odd counter

module odd_counter(input clk, rst, output logic [7:0]count);

logic [7:0] nxt_count;

always_ff @(posedge clk or posedge rst) begin
    if (rst) count <= 8'h1;
    else count <= nxt_count;
end

assign nxt_count = count + 8'h2;

endmodule

day5/day5_tb.sv
`timescale 1ns/1ps
`include "day5.sv"

module odd_counter_tb();
logic clk = 0, rst;
logic [7:0] count;

odd_counter OC(.clk(clk), .rst(rst), .count(count));

always #5 clk = ~clk;

initial begin
    rst <= 1'b1;
    @(posedge clk);
    @(posedge clk);
    rst <= 1'b0;
    for (int i=0; i<128; i++)
      @(posedge clk);
    $finish();
end

initial begin
    $dumpfile("odd_counter_tb.vcd");
    $dumpvars(0, odd_counter_tb);
end

endmodule

day5/odd_counter_tb.vcd
$date
	Thu Jul 10 20:31:32 2025
$end
$version
	Icarus Verilog
$end
$timescale
	1ps
$end
$scope module odd_counter_tb $end
$var wire 8 ! count [7:0] $end
$var reg 1 " clk $end
$var reg 1 # rst $end
$scope module OC $end
$var wire 1 " clk $end
$var wire 1 # rst $end
$var wire 8 $ nxt_count [7:0] $end
$var reg 8 % count [7:0] $end
$upscope $end
$scope begin $ivl_for_loop0 $end
$var integer 32 & i [31:0] $end
$upscope $end
$upscope $end
$enddefinitions $end
$comment Show the parameter values. $end
$dumpall
$end
#0
$dumpvars
b0 &
b1 %
b11 $
1#
0"
b1 !
$end
#5000
1"
#10000
0"
#15000
0#
1"
#20000
0"
#25000
b101 $
b11 !
b11 %
b1 &
1"
#30000
0"
#35000
b111 $
b101 !
b101 %
b10 &
1"
#40000
0"
#45000
b1001 $
b111 !
b111 %
b11 &
1"
#50000
0"
#55000
b1011 $
b1001 !
b1001 %
b100 &
1"
#60000
0"
#65000
b1101 $
b1011 !
b1011 %
b101 &
1"
#70000
0"
#75000
b1111 $
b1101 !
b1101 %
b110 &
1"
#80000
0"
#85000
b10001 $
b1111 !
b1111 %
b111 &
1"
#90000
0"
#95000
b10011 $
b10001 !
b10001 %
b1000 &
1"
#100000
0"
#105000
b10101 $
b10011 !
b10011 %
b1001 &
1"
#110000
0"
#115000
b10111 $
b10101 !
b10101 %
b1010 &
1"
#120000
0"
#125000
b11001 $
b10111 !
b10111 %
b1011 &
1"
#130000
0"
#135000
b11011 $
b11001 !
b11001 %
b1100 &
1"
#140000
0"
#145000
b11101 $
b11011 !
b11011 %
b1101 &
1"
#150000
0"
#155000
b11111 $
b11101 !
b11101 %
b1110 &
1"
#160000
0"
#165000
b100001 $
b11111 !
b11111 %
b1111 &
1"
#170000
0"
#175000
b100011 $
b100001 !
b100001 %
b10000 &
1"
#180000
0"
#185000
b100101 $
b100011 !
b100011 %
b10001 &
1"
#190000
0"
#195000
b100111 $
b100101 !
b100101 %
b10010 &
1"
#200000
0"
#205000
b101001 $
b100111 !
b100111 %
b10011 &
1"
#210000
0"
#215000
b101011 $
b101001 !
b101001 %
b10100 &
1"
#220000
0"
#225000
b101101 $
b101011 !
b101011 %
b10101 &
1"
#230000
0"
#235000
b101111 $
b101101 !
b101101 %
b10110 &
1"
#240000
0"
#245000
b110001 $
b101111 !
b101111 %
b10111 &
1"
#250000
0"
#255000
b110011 $
b110001 !
b110001 %
b11000 &
1"
#260000
0"
#265000
b110101 $
b110011 !
b110011 %
b11001 &
1"
#270000
0"
#275000
b110111 $
b110101 !
b110101 %
b11010 &
1"
#280000
0"
#285000
b111001 $
b110111 !
b110111 %
b11011 &
1"
#290000
0"
#295000
b111011 $
b111001 !
b111001 %
b11100 &
1"
#300000
0"
#305000
b111101 $
b111011 !
b111011 %
b11101 &
1"
#310000
0"
#315000
b111111 $
b111101 !
b111101 %
b11110 &
1"
#320000
0"
#325000
b1000001 $
b111111 !
b111111 %
b11111 &
1"
#330000
0"
#335000
b1000011 $
b1000001 !
b1000001 %
b100000 &
1"
#340000
0"
#345000
b1000101 $
b1000011 !
b1000011 %
b100001 &
1"
#350000
0"
#355000
b1000111 $
b1000101 !
b1000101 %
b100010 &
1"
#360000
0"
#365000
b1001001 $
b1000111 !
b1000111 %
b100011 &
1"
#370000
0"
#375000
b1001011 $
b1001001 !
b1001001 %
b100100 &
1"
#380000
0"
#385000
b1001101 $
b1001011 !
b1001011 %
b100101 &
1"
#390000
0"
#395000
b1001111 $
b1001101 !
b1001101 %
b100110 &
1"
#400000
0"
#405000
b1010001 $
b1001111 !
b1001111 %
b100111 &
1"
#410000
0"
#415000
b1010011 $
b1010001 !
b1010001 %
b101000 &
1"
#420000
0"
#425000
b1010101 $
b1010011 !
b1010011 %
b101001 &
1"
#430000
0"
#435000
b1010111 $
b1010101 !
b1010101 %
b101010 &
1"
#440000
0"
#445000
b1011001 $
b1010111 !
b1010111 %
b101011 &
1"
#450000
0"
#455000
b1011011 $
b1011001 !
b1011001 %
b101100 &
1"
#460000
0"
#465000
b1011101 $
b1011011 !
b1011011 %
b101101 &
1"
#470000
0"
#475000
b1011111 $
b1011101 !
b1011101 %
b101110 &
1"
#480000
0"
#485000
b1100001 $
b1011111 !
b1011111 %
b101111 &
1"
#490000
0"
#495000
b1100011 $
b1100001 !
b1100001 %
b110000 &
1"
#500000
0"
#505000
b1100101 $
b1100011 !
b1100011 %
b110001 &
1"
#510000
0"
#515000
b1100111 $
b1100101 !
b1100101 %
b110010 &
1"
#520000
0"
#525000
b1101001 $
b1100111 !
b1100111 %
b110011 &
1"
#530000
0"
#535000
b1101011 $
b1101001 !
b1101001 %
b110100 &
1"
#540000
0"
#545000
b1101101 $
b1101011 !
b1101011 %
b110101 &
1"
#550000
0"
#555000
b1101111 $
b1101101 !
b1101101 %
b110110 &
1"
#560000
0"
#565000
b1110001 $
b1101111 !
b1101111 %
b110111 &
1"
#570000
0"
#575000
b1110011 $
b1110001 !
b1110001 %
b111000 &
1"
#580000
0"
#585000
b1110101 $
b1110011 !
b1110011 %
b111001 &
1"
#590000
0"
#595000
b1110111 $
b1110101 !
b1110101 %
b111010 &
1"
#600000
0"
#605000
b1111001 $
b1110111 !
b1110111 %
b111011 &
1"
#610000
0"
#615000
b1111011 $
b1111001 !
b1111001 %
b111100 &
1"
#620000
0"
#625000
b1111101 $
b1111011 !
b1111011 %
b111101 &
1"
#630000
0"
#635000
b1111111 $
b1111101 !
b1111101 %
b111110 &
1"
#640000
0"
#645000
b10000001 $
b1111111 !
b1111111 %
b111111 &
1"
#650000
0"
#655000
b10000011 $
b10000001 !
b10000001 %
b1000000 &
1"
#660000
0"
#665000
b10000101 $
b10000011 !
b10000011 %
b1000001 &
1"
#670000
0"
#675000
b10000111 $
b10000101 !
b10000101 %
b1000010 &
1"
#680000
0"
#685000
b10001001 $
b10000111 !
b10000111 %
b1000011 &
1"
#690000
0"
#695000
b10001011 $
b10001001 !
b10001001 %
b1000100 &
1"
#700000
0"
#705000
b10001101 $
b10001011 !
b10001011 %
b1000101 &
1"
#710000
0"
#715000
b10001111 $
b10001101 !
b10001101 %
b1000110 &
1"
#720000
0"
#725000
b10010001 $
b10001111 !
b10001111 %
b1000111 &
1"
#730000
0"
#735000
b10010011 $
b10010001 !
b10010001 %
b1001000 &
1"
#740000
0"
#745000
b10010101 $
b10010011 !
b10010011 %
b1001001 &
1"
#750000
0"
#755000
b10010111 $
b10010101 !
b10010101 %
b1001010 &
1"
#760000
0"
#765000
b10011001 $
b10010111 !
b10010111 %
b1001011 &
1"
#770000
0"
#775000
b10011011 $
b10011001 !
b10011001 %
b1001100 &
1"
#780000
0"
#785000
b10011101 $
b10011011 !
b10011011 %
b1001101 &
1"
#790000
0"
#795000
b10011111 $
b10011101 !
b10011101 %
b1001110 &
1"
#800000
0"
#805000
b10100001 $
b10011111 !
b10011111 %
b1001111 &
1"
#810000
0"
#815000
b10100011 $
b10100001 !
b10100001 %
b1010000 &
1"
#820000
0"
#825000
b10100101 $
b10100011 !
b10100011 %
b1010001 &
1"
#830000
0"
#835000
b10100111 $
b10100101 !
b10100101 %
b1010010 &
1"
#840000
0"
#845000
b10101001 $
b10100111 !
b10100111 %
b1010011 &
1"
#850000
0"
#855000
b10101011 $
b10101001 !
b10101001 %
b1010100 &
1"
#860000
0"
#865000
b10101101 $
b10101011 !
b10101011 %
b1010101 &
1"
#870000
0"
#875000
b10101111 $
b10101101 !
b10101101 %
b1010110 &
1"
#880000
0"
#885000
b10110001 $
b10101111 !
b10101111 %
b1010111 &
1"
#890000
0"
#895000
b10110011 $
b10110001 !
b10110001 %
b1011000 &
1"
#900000
0"
#905000
b10110101 $
b10110011 !
b10110011 %
b1011001 &
1"
#910000
0"
#915000
b10110111 $
b10110101 !
b10110101 %
b1011010 &
1"
#920000
0"
#925000
b10111001 $
b10110111 !
b10110111 %
b1011011 &
1"
#930000
0"
#935000
b10111011 $
b10111001 !
b10111001 %
b1011100 &
1"
#940000
0"
#945000
b10111101 $
b10111011 !
b10111011 %
b1011101 &
1"
#950000
0"
#955000
b10111111 $
b10111101 !
b10111101 %
b1011110 &
1"
#960000
0"
#965000
b11000001 $
b10111111 !
b10111111 %
b1011111 &
1"
#970000
0"
#975000
b11000011 $
b11000001 !
b11000001 %
b1100000 &
1"
#980000
0"
#985000
b11000101 $
b11000011 !
b11000011 %
b1100001 &
1"
#990000
0"
#995000
b11000111 $
b11000101 !
b11000101 %
b1100010 &
1"
#1000000
0"
#1005000
b11001001 $
b11000111 !
b11000111 %
b1100011 &
1"
#1010000
0"
#1015000
b11001011 $
b11001001 !
b11001001 %
b1100100 &
1"
#1020000
0"
#1025000
b11001101 $
b11001011 !
b11001011 %
b1100101 &
1"
#1030000
0"
#1035000
b11001111 $
b11001101 !
b11001101 %
b1100110 &
1"
#1040000
0"
#1045000
b11010001 $
b11001111 !
b11001111 %
b1100111 &
1"
#1050000
0"
#1055000
b11010011 $
b11010001 !
b11010001 %
b1101000 &
1"
#1060000
0"
#1065000
b11010101 $
b11010011 !
b11010011 %
b1101001 &
1"
#1070000
0"
#1075000
b11010111 $
b11010101 !
b11010101 %
b1101010 &
1"
#1080000
0"
#1085000
b11011001 $
b11010111 !
b11010111 %
b1101011 &
1"
#1090000
0"
#1095000
b11011011 $
b11011001 !
b11011001 %
b1101100 &
1"
#1100000
0"
#1105000
b11011101 $
b11011011 !
b11011011 %
b1101101 &
1"
#1110000
0"
#1115000
b11011111 $
b11011101 !
b11011101 %
b1101110 &
1"
#1120000
0"
#1125000
b11100001 $
b11011111 !
b11011111 %
b1101111 &
1"
#1130000
0"
#1135000
b11100011 $
b11100001 !
b11100001 %
b1110000 &
1"
#1140000
0"
#1145000
b11100101 $
b11100011 !
b11100011 %
b1110001 &
1"
#1150000
0"
#1155000
b11100111 $
b11100101 !
b11100101 %
b1110010 &
1"
#1160000
0"
#1165000
b11101001 $
b11100111 !
b11100111 %
b1110011 &
1"
#1170000
0"
#1175000
b11101011 $
b11101001 !
b11101001 %
b1110100 &
1"
#1180000
0"
#1185000
b11101101 $
b11101011 !
b11101011 %
b1110101 &
1"
#1190000
0"
#1195000
b11101111 $
b11101101 !
b11101101 %
b1110110 &
1"
#1200000
0"
#1205000
b11110001 $
b11101111 !
b11101111 %
b1110111 &
1"
#1210000
0"
#1215000
b11110011 $
b11110001 !
b11110001 %
b1111000 &
1"
#1220000
0"
#1225000
b11110101 $
b11110011 !
b11110011 %
b1111001 &
1"
#1230000
0"
#1235000
b11110111 $
b11110101 !
b11110101 %
b1111010 &
1"
#1240000
0"
#1245000
b11111001 $
b11110111 !
b11110111 %
b1111011 &
1"
#1250000
0"
#1255000
b11111011 $
b11111001 !
b11111001 %
b1111100 &
1"
#1260000
0"
#1265000
b11111101 $
b11111011 !
b11111011 %
b1111101 &
1"
#1270000
0"
#1275000
b11111111 $
b11111101 !
b11111101 %
b1111110 &
1"
#1280000
0"
#1285000
b1 $
b11111111 !
b11111111 %
b1111111 &
1"
#1290000
0"
#1295000
b11 $
b1 !
b1 %
b10000000 &
1"
