day2/day2.sv
module dff(input clk, input rst, input d, output reg dff_norst, output reg dff_synrst, output reg dff_asyrst);
    always_ff @(posedge clk) begin 
        dff_norst <= d;        
    end

    always_ff @(posedge clk) begin
        if (rst) dff_synrst <= 1'b0;
        else dff_synrst <= d;
    end

    always_ff @(posedge clk or posedge rst) begin
        if (rst) dff_asyrst <= 1'b0;
        else dff_asyrst <= d;
    end
endmodule

day2/day2_tb.sv
`timescale 1ns/1ps
`include "day2.sv"

module dff_tb;
  logic clk = 0;         
  logic rst;
  logic d;
  logic dff_norst;
  logic dff_synrst;
  logic dff_asyrst;

  dff DFF (.*);         

  always  #5 clk = ~clk; 

  initial begin
    rst = 1'b1;
    d   = 1'b0;
    @(posedge clk);
    rst = 1'b0;
    @(posedge clk);
    d   = 1'b1;
    @(posedge clk); @(posedge clk);
    @(negedge clk);
    rst = 1'b1;
    @(posedge clk); @(posedge clk);
    rst = 1'b0;
    @(posedge clk); @(posedge clk);
    $finish;
  end

  // Dump VCD
  initial begin
    $dumpfile("dff_tb.vcd");
    $dumpvars(0, dff_tb);
  end

endmodule

day2/dff_tb.vcd
$date
	Thu Jul 10 00:36:38 2025
$end
$version
	Icarus Verilog
$end
$timescale
	1ps
$end
$scope module dff_tb $end
$var wire 1 ! dff_synrst $end
$var wire 1 " dff_norst $end
$var wire 1 # dff_asyrst $end
$var reg 1 $ clk $end
$var reg 1 % d $end
$var reg 1 & rst $end
$scope module DFF $end
$var wire 1 $ clk $end
$var wire 1 % d $end
$var wire 1 & rst $end
$var reg 1 # dff_asyrst $end
$var reg 1 " dff_norst $end
$var reg 1 ! dff_synrst $end
$upscope $end
$upscope $end
$enddefinitions $end
$comment Show the parameter values. $end
$dumpall
$end
#0
$dumpvars
1&
0%
0$
0#
x"
x!
$end
#5000
0"
0!
0&
1$
#10000
0$
#15000
1#
1%
1$
#20000
0$
#25000
1"
1!
1$
#30000
0$
#35000
1$
#40000
0#
1&
0$
#45000
0!
1$
#50000
0$
#55000
1#
0&
1$
#60000
0$
#65000
1!
1$
